{
  "name": "Дмитриев Осип Андреевич",
  "id": 1,
  "avMark": 3.7,
  "group": "A"
}{
  "name": "Семёнов Гаянэ Германович",
  "id": 3,
  "avMark": 3.6,
  "group": "C"
}{
  "name": "Игнатьев Юстиниан Христофорович",
  "id": 4,
  "avMark": 3.6,
  "group": "D"
}{
  "name": "Мухин Парамон Онисимович",
  "id": 6,
  "avMark": 3.9,
  "group": "E"
}{
  "name": "Анисимов Болеслав Германнович",
  "id": 7,
  "avMark": 3.9,
  "group": "E"
}{
  "name": "Игнатьев Гурий Григорьевич",
  "id": 8,
  "avMark": 3.8,
  "group": "A"
}{
  "name": "Никифоров Мстислав Куприянович",
  "id": 9,
  "avMark": 3.7,
  "group": "B"
}{
  "name": "Кулаков Корнелий Феликсович",
  "id": 12,
  "avMark": 3.7,
  "group": "D"
}{
  "name": "Мышкин Терентий Донатович",
  "id": 13,
  "avMark": 3.5,
  "group": "B"
}{
  "name": "Павлов Мирослав Николаевич",
  "id": 16,
  "avMark": 4.2,
  "group": "C"
}{
  "name": "Блинов Оскар Тихонович",
  "id": 17,
  "avMark": 3.9,
  "group": "A"
}{
  "name": "Кулагин Овидий Иванович",
  "id": 19,
  "avMark": 4.0,
  "group": "C"
}{
  "name": "Гаврилов Кассиан Тихонович",
  "id": 20,
  "avMark": 3.7,
  "group": "E"
}{
  "name": "Лукин Мартын Адольфович",
  "id": 21,
  "avMark": 3.7,
  "group": "D"
}{
  "name": "Бобылёв Святослав Тихонович",
  "id": 22,
  "avMark": 3.5,
  "group": "C"
}{
  "name": "Наумов Ермак Агафонович",
  "id": 23,
  "avMark": 3.6,
  "group": "E"
}{
  "name": "Зуев Герман Протасьевич",
  "id": 24,
  "avMark": 3.5,
  "group": "E"
}{
  "name": "Лебедев Аристарх Альвианович",
  "id": 26,
  "avMark": 3.5,
  "group": "B"
}{
  "name": "Романов Тимофей Кириллович",
  "id": 28,
  "avMark": 3.6,
  "group": "A"
}{
  "name": "Герасимов Ян Агафонович",
  "id": 29,
  "avMark": 3.5,
  "group": "A"
}{
  "name": "Казакова Веселина Юрьевна",
  "id": 33,
  "avMark": 3.6,
  "group": "D"
}{
  "name": "Андреева Илона Львовна",
  "id": 34,
  "avMark": 3.8,
  "group": "C"
}{
  "name": "Воробьёва Северина Валентиновна",
  "id": 35,
  "avMark": 3.7,
  "group": "C"
}{
  "name": "Сафонова Злата Рубеновна",
  "id": 36,
  "avMark": 3.6,
  "group": "E"
}{
  "name": "Полякова Аза Глебовна",
  "id": 37,
  "avMark": 3.6,
  "group": "E"
}{
  "name": "Капустина Инна Филатовна",
  "id": 38,
  "avMark": 4.2,
  "group": "A"
}{
  "name": "Уварова Эмилия Дмитриевна",
  "id": 39,
  "avMark": 3.5,
  "group": "B"
}{
  "name": "Пестова Габриэлла Васильевна",
  "id": 40,
  "avMark": 4.1,
  "group": "D"
}{
  "name": "Фомичёва Дарина Игнатьевна",
  "id": 41,
  "avMark": 3.7,
  "group": "A"
}{
  "name": "Кулакова Дарья Лукьевна",
  "id": 42,
  "avMark": 3.9,
  "group": "D"
}{
  "name": "Носкова Наталия Данииловна",
  "id": 44,
  "avMark": 3.5,
  "group": "A"
}{
  "name": "Федотова Артемида Васильевна",
  "id": 45,
  "avMark": 3.6,
  "group": "A"
}{
  "name": "Боброва Агнесса Ивановна",
  "id": 46,
  "avMark": 3.6,
  "group": "E"
}{
  "name": "Шилова Арина Федосеевна",
  "id": 48,
  "avMark": 3.9,
  "group": "E"
}{
  "name": "Абрамова Адель Максовна",
  "id": 50,
  "avMark": 3.9,
  "group": "C"
}{
  "name": "Титова Эмилия Никитевна",
  "id": 52,
  "avMark": 3.6,
  "group": "A"
}{
  "name": "Шарапова Янита Созоновна",
  "id": 53,
  "avMark": 4.0,
  "group": "A"
}{
  "name": "Зимина Александрина Константиновна",
  "id": 56,
  "avMark": 3.6,
  "group": "B"
}{
  "name": "Шубина Фрида Георгьевна",
  "id": 57,
  "avMark": 3.6,
  "group": "D"
}{
  "name": "Сидорова Янита Олеговна",
  "id": 58,
  "avMark": 3.8,
  "group": "B"
}